PyMca5/PyMcaDataDir.py
PyMca5/__init__.py
PyMca5/spslut.cpython-38-darwin.so
PyMca5/PyMcaMisc/__init__.py
PyMca5/PyMcaMisc/PhysicalMemory.py
PyMca5/PyMcaMisc/ProfilingUtils.py
PyMca5/PyMcaPlugins/Medfilt2DPlugin.py
PyMca5/PyMcaPlugins/MathPlugins.py
PyMca5/PyMcaPlugins/StackBrowserPlugin.py
PyMca5/PyMcaPlugins/MotorInfoWindow.py
PyMca5/PyMcaPlugins/StackNormalizationPlugin.py
PyMca5/PyMcaPlugins/MaskScatterViewPlugin.py
PyMca5/PyMcaPlugins/ExternalImagesStackPlugin.py
PyMca5/PyMcaPlugins/KineticsPlugin.py
PyMca5/PyMcaPlugins/SilxExternalImagesStackPlugin.py
PyMca5/PyMcaPlugins/StackAxesPlugin.py
PyMca5/PyMcaPlugins/ConsolePlugin.py
PyMca5/PyMcaPlugins/StackScanWindowPlugin.py
PyMca5/PyMcaPlugins/RegularMeshPlugin.py
PyMca5/PyMcaPlugins/ConsoleStackPlugin.py
PyMca5/PyMcaPlugins/XMCDPlugin.py
PyMca5/PyMcaPlugins/NNMAStackPlugin.py
PyMca5/PyMcaPlugins/ROIStackPlugin.py
PyMca5/PyMcaPlugins/LoadPositionersStackPlugin.py
PyMca5/PyMcaPlugins/__init__.py
PyMca5/PyMcaPlugins/FitAllCurvesPlugin.py
PyMca5/PyMcaPlugins/StackShowSpectra.py
PyMca5/PyMcaPlugins/PCAStackPlugin.py
PyMca5/PyMcaPlugins/BackgroundScanPlugin.py
PyMca5/PyMcaPlugins/FastXRFLinearFitStackPlugin.py
PyMca5/PyMcaPlugins/StackMotorInfoPlugin.py
PyMca5/PyMcaPlugins/NormalizationPlugins.py
PyMca5/PyMcaPlugins/StackPluginBase.py
PyMca5/PyMcaPlugins/MotorInfoPlugin.py
PyMca5/PyMcaPlugins/XASPlugin.py
PyMca5/PyMcaPlugins/AlignmentScanPlugin.py
PyMca5/PyMcaPlugins/MedianFilterScanPlugin.py
PyMca5/PyMcaPlugins/Plugin1DBase.py
PyMca5/PyMcaPlugins/SilxRoiStackPlugin.py
PyMca5/PyMcaPlugins/ReverseStackPlugin.py
PyMca5/PyMcaPlugins/FitStackPlugin.py
PyMca5/PyMcaPlugins/XASStackBatchPlugin.py
PyMca5/PyMcaPlugins/SimpleShift.py
PyMca5/PyMcaPlugins/AdvancedAlignmentScanPlugin.py
PyMca5/PyMcaPlugins/ImageAlignmentStackPlugin.py
PyMca5/PyMcaPlugins/MedianFilterStackPlugin.py
PyMca5/PyMcaPlugins/BackgroundStackPlugin.py
PyMca5/PyMcaPlugins/StackROIBatchPlugin.py
PyMca5-5.9.4.dist-info/LICENSE.LGPL
PyMca5-5.9.4.dist-info/LICENSE.MIT
PyMca5-5.9.4.dist-info/RECORD
PyMca5-5.9.4.dist-info/LICENSE
PyMca5-5.9.4.dist-info/LICENSE.GPL
PyMca5-5.9.4.dist-info/WHEEL
PyMca5-5.9.4.dist-info/top_level.txt
PyMca5-5.9.4.dist-info/METADATA
